hello_public_lib/__init__.py
hello_public_lib-0.0.2.dist-info/LICENSE
hello_public_lib-0.0.2.dist-info/WHEEL
hello_public_lib-0.0.2.dist-info/METADATA
hello_public_lib-0.0.2.dist-info/RECORD
