Metadata-Version: 2.1
Name: hello-public-lib
Version: 0.0.2
Summary: Awesome library
Author: Very Good Security
Author-email: dev@verygoodsecurity.com
Requires-Python: >=3.9,<4.0
Classifier: Programming Language :: Python :: 3
Classifier: Programming Language :: Python :: 3.9
